panxiaolan/File.py
panxiaolan/Hello.py
panxiaolan/Name.py
panxiaolan/__init__.py
panxiaolan_test/__init__.py
panxiaolan-0.2.1.dist-info/METADATA
panxiaolan-0.2.1.dist-info/WHEEL
panxiaolan-0.2.1.dist-info/top_level.txt
panxiaolan-0.2.1.dist-info/RECORD
