Metadata-Version: 2.1
Name: panxiaolan
Version: 0.2.1
Summary: AI Head
Home-page: https://github.com/XiaolanPan/Network
Author: panruijie
Author-email: panruijie0820@163.com
License: MIT
Platform: UNKNOWN
Classifier: License :: OSI Approved :: MIT License
Classifier: Programming Language :: Python
Classifier: Programming Language :: Python :: 3
Classifier: Programming Language :: Python :: 3.6
Classifier: Programming Language :: Python :: Implementation :: CPython
Classifier: Programming Language :: Python :: Implementation :: PyPy
Requires-Python: >=3.6.13
